LICENSE
MANIFEST.in
README.rst
setup.py
django_graphql_oauth2.egg-info/PKG-INFO
django_graphql_oauth2.egg-info/SOURCES.txt
django_graphql_oauth2.egg-info/dependency_links.txt
django_graphql_oauth2.egg-info/not-zip-safe
django_graphql_oauth2.egg-info/requires.txt
django_graphql_oauth2.egg-info/top_level.txt
provider/__init__.py
provider/constants.py
provider/decorators.py
provider/forms.py
provider/models.py
provider/scope.py
provider/utils.py
provider/views.py
provider/compat/__init__.py
provider/oauth2/__init__.py
provider/oauth2/admin.py
provider/oauth2/apps.py
provider/oauth2/backends.py
provider/oauth2/forms.py
provider/oauth2/middleware.py
provider/oauth2/mixins.py
provider/oauth2/models.py
provider/oauth2/views.py
provider/oauth2/migrations/0001_initial.py
provider/oauth2/migrations/0002_fix_scope_size.py
provider/oauth2/migrations/0003_public_client_options.py
provider/oauth2/migrations/__init__.py