Metadata-Version: 1.1
Name: django-graphql-oauth2
Version: 0.1.2
Summary: Provide OAuth2 access to your app (fork of django-oauth2)
Home-page: https://github.com/thisismkh/django-graphql-oauth2
Author: Mohammad
Author-email: UNKNOWN
License: The MIT License: http://www.opensource.org/licenses/mit-license.php
Platform: all
Classifier: Environment :: Web Environment
Classifier: Intended Audience :: Developers
Classifier: License :: OSI Approved :: MIT License
Classifier: Operating System :: OS Independent
Classifier: Programming Language :: Python
Classifier: Framework :: Django
